AUTHORS
FAQ
INSTALL
LICENSE
MANIFEST.in
NEWS
README
THANKS
TODO
build.vel
index.html
make_api_docs.sh
setup.py
docs/api/api-objects.txt
docs/api/class-tree.html
docs/api/crarr.png
docs/api/epydoc.css
docs/api/epydoc.js
docs/api/frames.html
docs/api/help.html
docs/api/identifier-index.html
docs/api/index.html
docs/api/module-tree.html
docs/api/redirect.html
docs/api/ternate-module.html
docs/api/ternate-pysrc.html
docs/api/ternate.cli-module.html
docs/api/ternate.cli-pysrc.html
docs/api/ternate.cli.Ternate-class.html
docs/api/ternate.utils-module.html
docs/api/ternate.utils-pysrc.html
docs/api/ternate.utils.NotFoundError-class.html
docs/api/toc-everything.html
docs/api/toc-ternate-module.html
docs/api/toc-ternate.cli-module.html
docs/api/toc-ternate.utils-module.html
docs/api/toc.html
examples/.foaf.rdf.swp
examples/example.sh
examples/foaf.rdf
ternate/__init__.py
ternate/cli.py
ternate/utils.py
ternate.egg-info/PKG-INFO
ternate.egg-info/SOURCES.txt
ternate.egg-info/dependency_links.txt
ternate.egg-info/entry_points.txt
ternate.egg-info/not-zip-safe
ternate.egg-info/requires.txt
ternate.egg-info/top_level.txt
xslt/developer.xsl