Metadata-Version: 1.0
Name: ternate
Version: 0.1.0
Summary: Tool to create FOAF and homepage for Gentoo Linux Developers
Home-page: http://trac.assembla.com/ternate
Author: Rob Cakebread
Author-email: <cakebread@gmail.com>
License: GPL-2
Keywords: foaf doap rdf gentoo semantic
Platform: UNKNOWN
Classifier: Development Status :: 2 - Pre-Alpha
Classifier: Intended Audience :: Developers
Classifier: Intended Audience :: End Users/Desktop
Classifier: License :: OSI Approved :: GNU General Public License (GPL)
Classifier: Programming Language :: Python
Classifier: Topic :: Software Development :: Libraries :: Python Modules
